figgypy/__init__.py
figgypy/config.py
figgypy/decrypt.py
figgypy/exceptions.py
figgypy/util.py
tests/__init__.py
tests/config_test.py
tests/decrypt_test.py
tests/util_test.py
figgypy-1.1.9.dist-info/LICENSE
figgypy-1.1.9.dist-info/METADATA
figgypy-1.1.9.dist-info/WHEEL
figgypy-1.1.9.dist-info/top_level.txt
figgypy-1.1.9.dist-info/RECORD
