Metadata-Version: 2.1
Name: figgypy
Version: 1.1.9
Summary: Simple configuration tool. Get config from yaml, json, or xml.
Home-page: https://github.com/theherk/figgypy
Author: Adam Sherwood
Author-email: theherk@gmail.com
License: MIT
Download-URL: https://github.com/theherk/figgypy/archive/1.2.dev.zip
Platform: all
Requires-Dist: boto3
Requires-Dist: future
Requires-Dist: pretty-bad-protocol
Requires-Dist: seria
Requires-Dist: pyyaml
